gen_ai_hub/__init__.py
gen_ai_hub/document_grounding/__init__.py
gen_ai_hub/document_grounding/client.py
gen_ai_hub/document_grounding/clients/__init__.py
gen_ai_hub/document_grounding/clients/pipeline_api_client.py
gen_ai_hub/document_grounding/clients/retrieval_api_client.py
gen_ai_hub/document_grounding/clients/vector_api_client.py
gen_ai_hub/document_grounding/models/__init__.py
gen_ai_hub/document_grounding/models/pipeline.py
gen_ai_hub/document_grounding/models/retrieval.py
gen_ai_hub/document_grounding/models/vector.py
gen_ai_hub/orchestration/__init__.py
gen_ai_hub/orchestration/exceptions.py
gen_ai_hub/orchestration/service.py
gen_ai_hub/orchestration/sse_client.py
gen_ai_hub/orchestration/utils.py
gen_ai_hub/orchestration/models/__init__.py
gen_ai_hub/orchestration/models/azure_content_filter.py
gen_ai_hub/orchestration/models/base.py
gen_ai_hub/orchestration/models/config.py
gen_ai_hub/orchestration/models/content_filter.py
gen_ai_hub/orchestration/models/content_filtering.py
gen_ai_hub/orchestration/models/data_masking.py
gen_ai_hub/orchestration/models/document_grounding.py
gen_ai_hub/orchestration/models/llama_guard_3_filter.py
gen_ai_hub/orchestration/models/llm.py
gen_ai_hub/orchestration/models/message.py
gen_ai_hub/orchestration/models/multimodal_items.py
gen_ai_hub/orchestration/models/response.py
gen_ai_hub/orchestration/models/response_format.py
gen_ai_hub/orchestration/models/sap_data_privacy_integration.py
gen_ai_hub/orchestration/models/template.py
gen_ai_hub/orchestration/models/template_ref.py
gen_ai_hub/orchestration/models/tools.py
gen_ai_hub/orchestration/models/translation/sap_document_translation.py
gen_ai_hub/orchestration/models/translation/translation.py
gen_ai_hub/prompt_registry/__init__.py
gen_ai_hub/prompt_registry/client.py
gen_ai_hub/prompt_registry/models/__init__.py
gen_ai_hub/prompt_registry/models/prompt_template.py
gen_ai_hub/proxy/__init__.py
gen_ai_hub/proxy/core/__init__.py
gen_ai_hub/proxy/core/base.py
sap_ai_sdk_gen-5.10.0.dist-info/LICENSE
sap_ai_sdk_gen-5.10.0.dist-info/METADATA
sap_ai_sdk_gen-5.10.0.dist-info/WHEEL
sap_ai_sdk_gen-5.10.0.dist-info/top_level.txt
sap_ai_sdk_gen-5.10.0.dist-info/RECORD
