Metadata-Version: 2.1
Name: sap-ai-sdk-gen
Version: 5.10.0
Summary: SAP Cloud SDK for AI (Python): generative AI SDK
Home-page: https://www.sap.com/
Author: SAP SE
License: SAP DEVELOPER LICENSE AGREEMENT
Download-URL: https://pypi.python.org/pypi/sap-ai-sdk-gen
Keywords: SAP AI Core,SAP generative AI SDK,SAP Generative AI Hub
Platform: Windows
Platform: Linux
Platform: Mac OS-X
Platform: Unix
Classifier: Development Status :: 5 - Production/Stable
Classifier: Intended Audience :: Developers
Classifier: License :: Other/Proprietary License
Classifier: Operating System :: MacOS :: MacOS X
Classifier: Operating System :: Microsoft :: Windows :: Windows 10
Classifier: Operating System :: Microsoft :: Windows :: Windows 7
Classifier: Operating System :: Microsoft :: Windows :: Windows 8
Classifier: Operating System :: Microsoft :: Windows :: Windows 8.1
Classifier: Operating System :: Microsoft :: Windows :: Windows Server 2008
Classifier: Operating System :: POSIX :: Linux
Classifier: Programming Language :: Python
Classifier: Programming Language :: Python :: 3
Classifier: Programming Language :: Python :: 3.9
Classifier: Programming Language :: Python :: 3.10
Classifier: Programming Language :: Python :: 3.11
Classifier: Programming Language :: Python :: 3.12
Classifier: Programming Language :: Python :: 3.13
Classifier: Topic :: Software Development :: Libraries :: Python Modules
Requires-Python: >=3.9
Requires-Dist: packaging (>=23.2)
Requires-Dist: sap-ai-sdk-core (>=3.1.0)
Requires-Dist: pydantic (~=2.12)
Requires-Dist: httpx (>=0.27.0)
Requires-Dist: openai (>=1.58.1)
Requires-Dist: langchain-openai (>=0.3.7)
Requires-Dist: h11 (>=0.16.0)
Requires-Dist: langchain-community (~=0.3.25)
Requires-Dist: dacite (>=1.8.1)
Requires-Dist: langchain (~=0.3.25)
Requires-Dist: click (>=8.1.7)
Requires-Dist: overloading (==0.5.0)
Provides-Extra: all
Requires-Dist: langchain-aws (~=0.2.35) ; extra == 'all'
Requires-Dist: langchain-google-vertexai (==2.1.1) ; extra == 'all'
Requires-Dist: google-cloud-aiplatform (==1.113.0) ; extra == 'all'
Requires-Dist: aioboto3 (==15.5.0) ; extra == 'all'
Requires-Dist: boto3 (==1.40.61) ; extra == 'all'
Provides-Extra: amazon
Requires-Dist: langchain-aws (~=0.2.35) ; extra == 'amazon'
Requires-Dist: boto3 (==1.40.61) ; extra == 'amazon'
Requires-Dist: aioboto3 (==15.5.0) ; extra == 'amazon'
Provides-Extra: google
Requires-Dist: google-cloud-aiplatform (==1.113.0) ; extra == 'google'
Requires-Dist: langchain-google-vertexai (==2.1.1) ; extra == 'google'
